teleshell/__init__.py
teleshell/classes.py
teleshell-0.0.6.dist-info/LICENSE
teleshell-0.0.6.dist-info/METADATA
teleshell-0.0.6.dist-info/WHEEL
teleshell-0.0.6.dist-info/top_level.txt
teleshell-0.0.6.dist-info/RECORD
