Metadata-Version: 2.1
Name: teleshell
Version: 0.0.6
Summary: A shell for telethon
Home-page: https://notabug.org/EgTer/teleshell
Author: EgTer
Author-email: annom2017@mail.ru
License: UNKNOWN
Platform: UNKNOWN
Classifier: Programming Language :: Python :: 3.7
Classifier: License :: OSI Approved :: GNU General Public License v3 (GPLv3)
Requires-Dist: telethon
